flatpak_node_generator/__init__.py
flatpak_node_generator/__main__.py
flatpak_node_generator/cache.py
flatpak_node_generator/electron.py
flatpak_node_generator/integrity.py
flatpak_node_generator/main.py
flatpak_node_generator/manifest.py
flatpak_node_generator/node_headers.py
flatpak_node_generator/package.py
flatpak_node_generator/progress.py
flatpak_node_generator/providers/__init__.py
flatpak_node_generator/providers/npm.py
flatpak_node_generator/providers/special.py
flatpak_node_generator/providers/yarn.py
flatpak_node_generator/py.typed
flatpak_node_generator/requests.py
flatpak_node_generator/url_metadata.py
flatpak_node_generator-0.1.1.dist-info/METADATA
flatpak_node_generator-0.1.1.dist-info/WHEEL
flatpak_node_generator-0.1.1.dist-info/entry_points.txt
flatpak_node_generator-0.1.1.dist-info/RECORD
