Metadata-Version: 2.1
Name: flatpak_node_generator
Version: 0.1.1
Summary: 
Author: Ryan Gonzalez
Author-email: ryan.gonzalez@collabora.com
Requires-Python: >=3.8,<4.0
Classifier: Programming Language :: Python :: 3
Classifier: Programming Language :: Python :: 3.8
Classifier: Programming Language :: Python :: 3.9
Classifier: Programming Language :: Python :: 3.10
Classifier: Programming Language :: Python :: 3.11
Classifier: Programming Language :: Python :: 3.12
Classifier: Programming Language :: Python :: 3.13
Requires-Dist: aiohttp (>=3.9.0,<4.0.0)
